fkptjax/__init__.py
fkptjax/calculate_jax.py
fkptjax/calculate_numpy.py
fkptjax/plot.py
fkptjax/snapshot.py
fkptjax/types.py
fkptjax/util.py
fkptjax-0.2.1.dist-info/licenses/LICENSE
fkptjax-0.2.1.dist-info/METADATA
fkptjax-0.2.1.dist-info/WHEEL
fkptjax-0.2.1.dist-info/top_level.txt
fkptjax-0.2.1.dist-info/RECORD
