Metadata-Version: 2.4
Name: fkptjax
Version: 0.2.1
Summary: Perturbation theory calculations for LCDM and Modified Gravity theories using fk-Kernels implemented in Python with JAX
Author-email: David Kirkby <dkirkby@uci.edu>, Matthew Dowicz <mdowicz@uci.edu>
License: MIT
Project-URL: Homepage, https://github.com/cosmodesi/fkptjax
Project-URL: Repository, https://github.com/cosmodesi/fkptjax
Keywords: cosmology,perturbation-theory,modified-gravity,jax
Classifier: Development Status :: 3 - Alpha
Classifier: Intended Audience :: Science/Research
Classifier: License :: OSI Approved :: MIT License
Classifier: Programming Language :: Python :: 3
Classifier: Programming Language :: Python :: 3.10
Classifier: Programming Language :: Python :: 3.11
Classifier: Programming Language :: Python :: 3.12
Classifier: Topic :: Scientific/Engineering :: Physics
Classifier: Topic :: Scientific/Engineering :: Astronomy
Requires-Python: >=3.10
License-File: LICENSE
Requires-Dist: jax>=0.4.0
Requires-Dist: jaxlib>=0.4.0
Requires-Dist: numpy>=1.24.0
Requires-Dist: scipy>=1.10.0
Provides-Extra: dev
Requires-Dist: pytest>=7.0; extra == "dev"
Requires-Dist: pytest-cov>=4.0; extra == "dev"
Requires-Dist: mypy>=1.0; extra == "dev"
Dynamic: license-file
